sitzungsexport/__init__.py
sitzungsexport/bookstack.py
sitzungsexport/cli.py
sitzungsexport/models.py
sitzungsexport/replacements.py
sitzungsexport-0.2.2.dist-info/LICENSE
sitzungsexport-0.2.2.dist-info/METADATA
sitzungsexport-0.2.2.dist-info/WHEEL
sitzungsexport-0.2.2.dist-info/entry_points.txt
sitzungsexport-0.2.2.dist-info/top_level.txt
sitzungsexport-0.2.2.dist-info/RECORD
